{
    "metadata": {
        "url_consultada": "https://dadosabertos.compras.gov.br/modulo-legado/6.1_consultarItensComprasSemLicitacao_Id?id_compra=15845406000222018",
        "data_extracao": "2026-02-13 11:33:13",
        "status": "SUCESSO"
    },
    "respostas": {
        "resultado": [
            {
                "idCompra": "15845406000222018",
                "idCompraItem": "1584540600022201800001",
                "coUasg": 158454,
                "coModalidadeLicitacao": 6,
                "noModalidadeLicitacao": "Dispensa",
                "nuAvisoLicitacao": 22,
                "dtAnoAvisoLicitacao": 2018,
                "nuInciso": "02",
                "nuProcesso": "23347012143201886",
                "vrEstimado": 2150.0,
                "qtTotalItem": 2,
                "dsObjetoLicitacao": null,
                "dsFundamentoLegal": "Fundamento Legal: Art. 24º, Inciso II da Lei nº 8.666 de 21/06/1993.",
                "dsJustificativa": "Justificativa: Valor abaixo de R$ 17.600",
                "nuCpfRespDeclDisp": null,
                "nuCpfRespRatificacao": null,
                "nuCpfRespPublicacao": null,
                "noResponsavelDeclDisp": "APIO CARNIELO E SILVA",
                "noCargoRespDeclDisp": "Ordenador de Despesas",
                "noResponsavelRatificacao": "",
                "noCargoRespRatificacao": "",
                "nuItemMaterial": 1,
                "inMaterialServico": "material",
                "coConjuntoMateriais": 138282,
                "noConjuntoMateriais": "PASTA ARQUIVO",
                "coServico": 0,
                "noServico": null,
                "dsDetalhada": "PASTA ARQUIVO, Pasta de estudante: pasta 32cm x 46cm (tamanho aberto), 1 lâmin a em papel cartão massa úmida (pode ser também supremo ou duo design), gramatu ra 250g/m², cores 4/0 (colorido frente), 01 dobra e vinco no meio, refile, com  arte a ser fornecida.",
                "qtMaterialAlt": 4000,
                "noUnidadeMedida": "Unidade",
                "vrEstimadoItem": 1500.0,
                "dsFabricante": null,
                "noMarcaMaterial": "Não Especificado",
                "inTipoFornecedorVencedor": "PJ",
                "nuCnpjVencedor": "36812295000229",
                "nuCpfVencedor": null,
                "noFornecedorVencedor": "LARSEN & LARSEN LTDA",
                "dtAlteracao": "2024-04-08T11:45:00"
            },
            {
                "idCompra": "15845406000222018",
                "idCompraItem": "1584540600022201800002",
                "coUasg": 158454,
                "coModalidadeLicitacao": 6,
                "noModalidadeLicitacao": "Dispensa",
                "nuAvisoLicitacao": 22,
                "dtAnoAvisoLicitacao": 2018,
                "nuInciso": "02",
                "nuProcesso": "23347012143201886",
                "vrEstimado": 2150.0,
                "qtTotalItem": 2,
                "dsObjetoLicitacao": null,
                "dsFundamentoLegal": "Fundamento Legal: Art. 24º, Inciso II da Lei nº 8.666 de 21/06/1993.",
                "dsJustificativa": "Justificativa: Valor abaixo de R$ 17.600",
                "nuCpfRespDeclDisp": null,
                "nuCpfRespRatificacao": null,
                "nuCpfRespPublicacao": null,
                "noResponsavelDeclDisp": "APIO CARNIELO E SILVA",
                "noCargoRespDeclDisp": "Ordenador de Despesas",
                "noResponsavelRatificacao": "",
                "noCargoRespRatificacao": "",
                "nuItemMaterial": 2,
                "inMaterialServico": "material",
                "coConjuntoMateriais": 965,
                "noConjuntoMateriais": "PAPEL",
                "coServico": 0,
                "noServico": null,
                "dsDetalhada": "Modelo certificado - Couche gramatura 180g, tamanho A4, impressão colorida em apenas um lado, com arte a ser fornecida.",
                "qtMaterialAlt": 1000,
                "noUnidadeMedida": "Unidade",
                "vrEstimadoItem": 650.0,
                "dsFabricante": null,
                "noMarcaMaterial": "Não Especificado",
                "inTipoFornecedorVencedor": "PJ",
                "nuCnpjVencedor": "36812295000229",
                "nuCpfVencedor": null,
                "noFornecedorVencedor": "LARSEN & LARSEN LTDA",
                "dtAlteracao": "2024-04-08T11:45:00"
            }
        ],
        "totalRegistros": 2,
        "totalPaginas": 1,
        "paginasRestantes": 0
    }
}