{
    "metadata": {
        "url_consultada": "https://dadosabertos.compras.gov.br/modulo-legado/4.1_consultarItensPregoes_Id?id_compra=15845105000032017",
        "data_extracao": "2026-02-13 11:41:12",
        "status": "SUCESSO"
    },
    "respostas": {
        "resultado": [
            {
                "tbVwItensPregaoId": {
                    "coUasg": 158451,
                    "coItem": 19046334
                },
                "decreto7174": "FALSE",
                "descricaoDetalhadaItem": "BALANÇA MÉDICA MECÂNICA, antropométrica, com capacidade aproximada de 150 quilos, frações de 100 gramas, dotada de escala antropométrica, com altura aproximada de 2,00 metros, com dimensões de 0,5 cm. Base de ferro fundido laminado reforçado. Plataforma em chapa de aço reforçado pintado, com tapete de borracha antiderrapante, pintura uniforme com tratamento anti-ferruginoso. Todas as despesas com transporte, entrega, carregamento e descarregamento correrão por conta do licitante.",
                "descricaoItem": "BALANÇA MECÂNICA",
                "fornecedorVencedor": null,
                "margemPreferencial": "FALSE",
                "menorLance": "762.97",
                "quantidadeItem": "3",
                "situacaoItem": "homologado",
                "tratamentoDiferenciado": null,
                "unidadeFornecimento": "UNIDADE",
                "valorHomologadoItem": "762.97",
                "valorEstimadoItem": "858.99",
                "valorNegociado": null,
                "idCompra": "15845105000032017",
                "idCompraItem": "1584510500003201700047",
                "noAdjudic": "BIANCA CAROLINA GONCALVES VIANA",
                "noHom": "PAULA VIANNA",
                "dtEncerramento": "2017-10-26",
                "dtAdjudic": "2017-10-27",
                "dtHom": "2017-10-30",
                "dtAlteracao": "2024-04-08T11:32:00"
            },
            {
                "tbVwItensPregaoId": {
                    "coUasg": 158451,
                    "coItem": 19046333
                },
                "decreto7174": "FALSE",
                "descricaoDetalhadaItem": "SERINGA, MATERIAL POLIPROPILENO, CAPACIDADE 20 ML, TIPO BICO BICO CENTRAL LUERLOCK OU SLIP, TIPO VEDAÇÃO ÊMBOLO DE BORRACHA, ADICIONAL GRADUADA, NUMERADA,  ESTERILIDADE ESTÉRIL, DESCARTÁVEL, APRESENTAÇÃO EMBALAGEM INDIVIDUAL",
                "descricaoItem": "SERINGA",
                "fornecedorVencedor": null,
                "margemPreferencial": "TRUE",
                "menorLance": "35.90",
                "quantidadeItem": "7",
                "situacaoItem": "homologado",
                "tratamentoDiferenciado": null,
                "unidadeFornecimento": "UNIDADE",
                "valorHomologadoItem": "35.90",
                "valorEstimadoItem": "54.57",
                "valorNegociado": null,
                "idCompra": "15845105000032017",
                "idCompraItem": "1584510500003201700046",
                "noAdjudic": "BIANCA CAROLINA GONCALVES VIANA",
                "noHom": "PAULA VIANNA",
                "dtEncerramento": "2017-10-26",
                "dtAdjudic": "2017-10-27",
                "dtHom": "2017-10-30",
                "dtAlteracao": "2024-04-08T11:32:00"
            },
            {
                "tbVwItensPregaoId": {
                    "coUasg": 158451,
                    "coItem": 19046332
                },
                "decreto7174": "FALSE",
                "descricaoDetalhadaItem": "CONJUNTO PROCEDIMENTO MÉDICO, APLICAÇÃO P/ CURATIVO, COMPOSIÇÃO BÁSICA C/     CAMPO CIRÚRGICO E CERCA DE 3 PINÇAS, ESTERILIDADE ESTÉRIL, USO ÚNICO",
                "descricaoItem": "CONJUNTO PROCEDIMENTO MÉDICO",
                "fornecedorVencedor": null,
                "margemPreferencial": "TRUE",
                "menorLance": "20.80",
                "quantidadeItem": "201",
                "situacaoItem": "cancelado no julgamento",
                "tratamentoDiferenciado": null,
                "unidadeFornecimento": "UNIDADE",
                "valorHomologadoItem": null,
                "valorEstimadoItem": "18.07",
                "valorNegociado": null,
                "idCompra": "15845105000032017",
                "idCompraItem": "1584510500003201700045",
                "noAdjudic": "BIANCA CAROLINA GONCALVES VIANA",
                "noHom": "PAULA VIANNA",
                "dtEncerramento": "2017-10-26",
                "dtAdjudic": "2017-10-27",
                "dtHom": "2017-10-30",
                "dtAlteracao": "2024-04-08T11:32:00"
            },
            {
                "tbVwItensPregaoId": {
                    "coUasg": 158451,
                    "coItem": 19046331
                },
                "decreto7174": "FALSE",
                "descricaoDetalhadaItem": "CUBA USO HOSPITALAR, MATERIAL AÇO INOXIDÁVEL, FORMATO RETANGULAR, COMPRIMENTO 25 CM, LARGURA 12 CM, PROFUNDIDADE 5 CM",
                "descricaoItem": "CUBA USO HOSPITALAR",
                "fornecedorVencedor": null,
                "margemPreferencial": "FALSE",
                "menorLance": "31.89",
                "quantidadeItem": "11",
                "situacaoItem": "homologado",
                "tratamentoDiferenciado": null,
                "unidadeFornecimento": "UNIDADE",
                "valorHomologadoItem": "31.89",
                "valorEstimadoItem": "45.36",
                "valorNegociado": null,
                "idCompra": "15845105000032017",
                "idCompraItem": "1584510500003201700044",
                "noAdjudic": "BIANCA CAROLINA GONCALVES VIANA",
                "noHom": "PAULA VIANNA",
                "dtEncerramento": "2017-10-26",
                "dtAdjudic": "2017-10-27",
                "dtHom": "2017-10-30",
                "dtAlteracao": "2024-04-08T11:32:00"
            },
            {
                "tbVwItensPregaoId": {
                    "coUasg": 158451,
                    "coItem": 19046330
                },
                "decreto7174": "FALSE",
                "descricaoDetalhadaItem": "BACIA - USO HOSPITALAR, MATERIAL AÇO INOXIDÁVEL, DIÂMETRO CERCA DE 35 CM,     CAPACIDADE CERCA DE 3000 ML, ESTERILIDADE ESTERILIZÁVEL",
                "descricaoItem": "BACIA - USO HOSPITALAR",
                "fornecedorVencedor": null,
                "margemPreferencial": "FALSE",
                "menorLance": "51.00",
                "quantidadeItem": "11",
                "situacaoItem": "homologado",
                "tratamentoDiferenciado": null,
                "unidadeFornecimento": "UNIDADE",
                "valorHomologadoItem": "51.00",
                "valorEstimadoItem": "53.93",
                "valorNegociado": null,
                "idCompra": "15845105000032017",
                "idCompraItem": "1584510500003201700043",
                "noAdjudic": "BIANCA CAROLINA GONCALVES VIANA",
                "noHom": "PAULA VIANNA",
                "dtEncerramento": "2017-10-26",
                "dtAdjudic": "2017-10-27",
                "dtHom": "2017-10-30",
                "dtAlteracao": "2024-04-08T11:32:00"
            },
            {
                "tbVwItensPregaoId": {
                    "coUasg": 158451,
                    "coItem": 19046329
                },
                "decreto7174": "FALSE",
                "descricaoDetalhadaItem": "TERMÔMETRO, TIPO DIGITAL, APLICAÇÃO HOSPITALAR, COMPRIMENTO 120 MM,           CARACTERÍSTICAS ADICIONAIS BOTÃO LIGA/DESLIGA/ MEMÓRIA/ DESLIGAMENTO AUTO-,   LARGURA 17,5 MM, ESPESSURA 8,5 MM, TIPO HASTE FLEXÍVEL A UM ÂNGULO DE 4 A 5   GRÁUS., MATERIAL BULBO METÁLICO",
                "descricaoItem": "TERMÔMETRO",
                "fornecedorVencedor": null,
                "margemPreferencial": "FALSE",
                "menorLance": "17.92",
                "quantidadeItem": "21",
                "situacaoItem": "homologado",
                "tratamentoDiferenciado": null,
                "unidadeFornecimento": "UNIDADE",
                "valorHomologadoItem": "17.92",
                "valorEstimadoItem": "18.76",
                "valorNegociado": null,
                "idCompra": "15845105000032017",
                "idCompraItem": "1584510500003201700042",
                "noAdjudic": "BIANCA CAROLINA GONCALVES VIANA",
                "noHom": "PAULA VIANNA",
                "dtEncerramento": "2017-10-26",
                "dtAdjudic": "2017-10-27",
                "dtHom": "2017-10-30",
                "dtAlteracao": "2024-04-08T11:32:00"
            },
            {
                "tbVwItensPregaoId": {
                    "coUasg": 158451,
                    "coItem": 19046328
                },
                "decreto7174": "FALSE",
                "descricaoDetalhadaItem": "TESOURA, MATERIAL AÇO INOXIDÁVEL, COMPRIMENTO 12 CM, TIPO PONTA RETA,         CARACTERÍSTICAS ADICIONAIS C/ 2PONTAS FINAS, TIPO ÍRIS",
                "descricaoItem": "TESOURA",
                "fornecedorVencedor": null,
                "margemPreferencial": "FALSE",
                "menorLance": "15.89",
                "quantidadeItem": "11",
                "situacaoItem": "homologado",
                "tratamentoDiferenciado": null,
                "unidadeFornecimento": "UNIDADE",
                "valorHomologadoItem": "15.89",
                "valorEstimadoItem": "22.91",
                "valorNegociado": null,
                "idCompra": "15845105000032017",
                "idCompraItem": "1584510500003201700041",
                "noAdjudic": "BIANCA CAROLINA GONCALVES VIANA",
                "noHom": "PAULA VIANNA",
                "dtEncerramento": "2017-10-26",
                "dtAdjudic": "2017-10-27",
                "dtHom": "2017-10-30",
                "dtAlteracao": "2024-04-08T11:32:00"
            },
            {
                "tbVwItensPregaoId": {
                    "coUasg": 158451,
                    "coItem": 19046327
                },
                "decreto7174": "FALSE",
                "descricaoDetalhadaItem": "TALA ORTOPÉDICA, MATERIAL ETIL VINIL ACETATO (EVA), TIPO C/ TELA ARAMADA,     MOLDAVEL, TAMANHO CERCA DE 30 CM X 8 CM, CARACTERÍSTICAS ADICIONAIS USO ÚNICO",
                "descricaoItem": "TALA ORTOPÉDICA",
                "fornecedorVencedor": null,
                "margemPreferencial": "FALSE",
                "menorLance": "75.99",
                "quantidadeItem": "21",
                "situacaoItem": "homologado",
                "tratamentoDiferenciado": null,
                "unidadeFornecimento": "UNIDADE",
                "valorHomologadoItem": "75.99",
                "valorEstimadoItem": "87.27",
                "valorNegociado": null,
                "idCompra": "15845105000032017",
                "idCompraItem": "1584510500003201700040",
                "noAdjudic": "BIANCA CAROLINA GONCALVES VIANA",
                "noHom": "PAULA VIANNA",
                "dtEncerramento": "2017-10-26",
                "dtAdjudic": "2017-10-27",
                "dtHom": "2017-10-30",
                "dtAlteracao": "2024-04-08T11:32:00"
            },
            {
                "tbVwItensPregaoId": {
                    "coUasg": 158451,
                    "coItem": 19046326
                },
                "decreto7174": "FALSE",
                "descricaoDetalhadaItem": "CLORETO DE SÓDIO, PRINCÍPIO ATIVO 0,9%_ SOLUÇÃO INJETÁVEL, APLICAÇÃO SISTEMA  FECHADO",
                "descricaoItem": "CLORETO DE SÓDIO",
                "fornecedorVencedor": null,
                "margemPreferencial": "FALSE",
                "menorLance": "3.55",
                "quantidadeItem": "140",
                "situacaoItem": "homologado",
                "tratamentoDiferenciado": null,
                "unidadeFornecimento": "FRASCO 100,00 ML",
                "valorHomologadoItem": "3.55",
                "valorEstimadoItem": "4.66",
                "valorNegociado": null,
                "idCompra": "15845105000032017",
                "idCompraItem": "1584510500003201700039",
                "noAdjudic": "BIANCA CAROLINA GONCALVES VIANA",
                "noHom": "PAULA VIANNA",
                "dtEncerramento": "2017-10-26",
                "dtAdjudic": "2017-10-27",
                "dtHom": "2017-10-30",
                "dtAlteracao": "2024-04-08T11:32:00"
            },
            {
                "tbVwItensPregaoId": {
                    "coUasg": 158451,
                    "coItem": 19046325
                },
                "decreto7174": "FALSE",
                "descricaoDetalhadaItem": "SAIS PARA REIDRATAÇÃO ORAL, APRESENTAÇÃO LÍQUIDO, COMPOSIÇÃO COMPOSTO POR     CLORETOS DE SÓDIO E POTÁSSIO, GLICOS E, COMPONENTE ADICIONAL CITRATO DE SÓDIO,CONCENTRAÇÃO 2,34 MG + 1,49 MG + 19,83 MG + 1,96 MG/ML, FORMA FARMACÊUTICA EM SOLUÇÃO ORAL",
                "descricaoItem": "SAIS PARA REIDRATAÇÃO ORAL",
                "fornecedorVencedor": null,
                "margemPreferencial": "FALSE",
                "menorLance": "17.95",
                "quantidadeItem": "215",
                "situacaoItem": "homologado",
                "tratamentoDiferenciado": null,
                "unidadeFornecimento": "ENVELOPE",
                "valorHomologadoItem": "17.95",
                "valorEstimadoItem": "21.65",
                "valorNegociado": null,
                "idCompra": "15845105000032017",
                "idCompraItem": "1584510500003201700038",
                "noAdjudic": "BIANCA CAROLINA GONCALVES VIANA",
                "noHom": "PAULA VIANNA",
                "dtEncerramento": "2017-10-26",
                "dtAdjudic": "2017-10-27",
                "dtHom": "2017-10-30",
                "dtAlteracao": "2024-04-08T11:32:00"
            },
            {
                "tbVwItensPregaoId": {
                    "coUasg": 158451,
                    "coItem": 19046320
                },
                "decreto7174": "FALSE",
                "descricaoDetalhadaItem": "MÁSCARA, TIPO P/ PROTEÇÃO CONTRA BACILO DE BAAR, CARACTERÍSTICAS ADICIONAIS C/FILTRO PFF2",
                "descricaoItem": "MÁSCARA",
                "fornecedorVencedor": null,
                "margemPreferencial": "FALSE",
                "menorLance": "3.11",
                "quantidadeItem": "310",
                "situacaoItem": "homologado",
                "tratamentoDiferenciado": null,
                "unidadeFornecimento": "UNIDADE",
                "valorHomologadoItem": "3.11",
                "valorEstimadoItem": "5.11",
                "valorNegociado": null,
                "idCompra": "15845105000032017",
                "idCompraItem": "1584510500003201700033",
                "noAdjudic": "BIANCA CAROLINA GONCALVES VIANA",
                "noHom": "PAULA VIANNA",
                "dtEncerramento": "2017-10-26",
                "dtAdjudic": "2017-10-27",
                "dtHom": "2017-10-30",
                "dtAlteracao": "2024-04-08T11:32:00"
            },
            {
                "tbVwItensPregaoId": {
                    "coUasg": 158451,
                    "coItem": 19046319
                },
                "decreto7174": "FALSE",
                "descricaoDetalhadaItem": "LUVA CIRÚRGICA, MATERIAL LÁTEX NATURAL, TAMANHO 7,50, ESTERILIDADE ESTÉRIL,   CARACTERÍSTICAS ADICIONAIS COMPRIMENTO MÍNIMO DE 28CM, APRESENTAÇÃO           LUBRIFICADA C/ PÓ BIOABSORVÍVEL,ATÓXICA, TIPO USO DESCARTÁVEL, FORMATO        ANATÔMICO, APLICAÇÃO ANTIDERRAPANTE, EMBALAGEM CONFORME NORMA ABNT C/ ABERTURAASSÉPTICA",
                "descricaoItem": "LUVA CIRÚRGICA",
                "fornecedorVencedor": null,
                "margemPreferencial": "TRUE",
                "menorLance": "14.70",
                "quantidadeItem": "310",
                "situacaoItem": "homologado",
                "tratamentoDiferenciado": null,
                "unidadeFornecimento": "PAR",
                "valorHomologadoItem": "14.70",
                "valorEstimadoItem": "21.28",
                "valorNegociado": null,
                "idCompra": "15845105000032017",
                "idCompraItem": "1584510500003201700032",
                "noAdjudic": "BIANCA CAROLINA GONCALVES VIANA",
                "noHom": "PAULA VIANNA",
                "dtEncerramento": "2017-10-26",
                "dtAdjudic": "2017-10-27",
                "dtHom": "2017-10-30",
                "dtAlteracao": "2024-04-08T11:32:00"
            },
            {
                "tbVwItensPregaoId": {
                    "coUasg": 158451,
                    "coItem": 19046318
                },
                "decreto7174": "FALSE",
                "descricaoDetalhadaItem": "Lanterna clínica lâmpada em LED, corpo de metal, interruptor emborrachado na parte superior, uso de pilhas alcalinas. Dimensões aproximadas: comp. 14,5cm, diâm. 1,7cm. Todas as despesas com transporte, entrega, carregamento e descarregamento correrão por conta do licitante.",
                "descricaoItem": "LANTERNA NÃO ELÉTRICA",
                "fornecedorVencedor": null,
                "margemPreferencial": "FALSE",
                "menorLance": "25.99",
                "quantidadeItem": "11",
                "situacaoItem": "homologado",
                "tratamentoDiferenciado": null,
                "unidadeFornecimento": "UNIDADE",
                "valorHomologadoItem": "25.99",
                "valorEstimadoItem": "26.96",
                "valorNegociado": null,
                "idCompra": "15845105000032017",
                "idCompraItem": "1584510500003201700031",
                "noAdjudic": "BIANCA CAROLINA GONCALVES VIANA",
                "noHom": "PAULA VIANNA",
                "dtEncerramento": "2017-10-26",
                "dtAdjudic": "2017-10-27",
                "dtHom": "2017-10-30",
                "dtAlteracao": "2024-04-08T11:32:00"
            },
            {
                "tbVwItensPregaoId": {
                    "coUasg": 158451,
                    "coItem": 19046317
                },
                "decreto7174": "FALSE",
                "descricaoDetalhadaItem": "LÂMINA BISTURI, MATERIAL AÇO CARBONO, TAMANHO Nº 15, TIPO DESCARTÁVEL,        ESTERILIDADE ESTÉRIL, CARACTERÍSTICAS ADICIONAIS EMBALADA INDIVIDUALMENTE",
                "descricaoItem": "LÂMINA BISTURI",
                "fornecedorVencedor": null,
                "margemPreferencial": "FALSE",
                "menorLance": "28.54",
                "quantidadeItem": "6",
                "situacaoItem": "homologado",
                "tratamentoDiferenciado": null,
                "unidadeFornecimento": "CAIXA 100,00 UN",
                "valorHomologadoItem": "28.54",
                "valorEstimadoItem": "35.69",
                "valorNegociado": null,
                "idCompra": "15845105000032017",
                "idCompraItem": "1584510500003201700030",
                "noAdjudic": "BIANCA CAROLINA GONCALVES VIANA",
                "noHom": "PAULA VIANNA",
                "dtEncerramento": "2017-10-26",
                "dtAdjudic": "2017-10-27",
                "dtHom": "2017-10-30",
                "dtAlteracao": "2024-04-08T11:32:00"
            },
            {
                "tbVwItensPregaoId": {
                    "coUasg": 158451,
                    "coItem": 19046316
                },
                "decreto7174": "FALSE",
                "descricaoDetalhadaItem": "REANIMADOR, MATERIAL SILICONE, TIPO MANUAL, CAPACIDADE BOLSA E VÁLVULA        VINIL,2500ML,CONEXÃO 6MM ML, CARACTERÍSTICAS ADICIONAIS VÁLV.INSPIRATÓRIA     UNIDIRECIONAL,DE ALÍVIO 40CM/H2 O, COMPONENTES MÁSCARA E BALÃO SILICONE,VOLUME500ML EXPIRATÓRIO, TAMANHO TAMANHO INFANTIL",
                "descricaoItem": "REANIMADOR",
                "fornecedorVencedor": null,
                "margemPreferencial": "FALSE",
                "menorLance": "247.00",
                "quantidadeItem": "5",
                "situacaoItem": "homologado",
                "tratamentoDiferenciado": null,
                "unidadeFornecimento": "UNIDADE",
                "valorHomologadoItem": "200.00",
                "valorEstimadoItem": "200.49",
                "valorNegociado": "200.00",
                "idCompra": "15845105000032017",
                "idCompraItem": "1584510500003201700029",
                "noAdjudic": "BIANCA CAROLINA GONCALVES VIANA",
                "noHom": "PAULA VIANNA",
                "dtEncerramento": "2017-10-26",
                "dtAdjudic": "2017-10-27",
                "dtHom": "2017-10-30",
                "dtAlteracao": "2024-04-08T11:32:00"
            },
            {
                "tbVwItensPregaoId": {
                    "coUasg": 158451,
                    "coItem": 19046315
                },
                "decreto7174": "FALSE",
                "descricaoDetalhadaItem": "REAGENTE PARA DIAGNÓSTICO CLÍNICO, TIPO DE ANÁLISE QUANTITATIVO DE GLICOSE,   CARACTERÍSTICAS ADICIONAIS CAPILAR, VENOSO, ARTERIAL OU NEONATAL, APRESENTAÇÃOTIRA",
                "descricaoItem": "REAGENTE PARA DIAGNÓSTICO CLÍNICO",
                "fornecedorVencedor": null,
                "margemPreferencial": "FALSE",
                "menorLance": "64.92",
                "quantidadeItem": "15",
                "situacaoItem": "homologado",
                "tratamentoDiferenciado": null,
                "unidadeFornecimento": "CAIXA 50,00 UN",
                "valorHomologadoItem": "64.92",
                "valorEstimadoItem": "67.31",
                "valorNegociado": null,
                "idCompra": "15845105000032017",
                "idCompraItem": "1584510500003201700028",
                "noAdjudic": "BIANCA CAROLINA GONCALVES VIANA",
                "noHom": "PAULA VIANNA",
                "dtEncerramento": "2017-10-26",
                "dtAdjudic": "2017-10-27",
                "dtHom": "2017-10-30",
                "dtAlteracao": "2024-04-08T11:32:00"
            },
            {
                "tbVwItensPregaoId": {
                    "coUasg": 158451,
                    "coItem": 19046314
                },
                "decreto7174": "FALSE",
                "descricaoDetalhadaItem": "MONITOR PORTÁTIL, OPERAÇÃO DIGITAL, TIPO AMOSTRA SANGUE CAPILAR, TIPO DE      ANÁLISE DOSAGEM GLICOSE,COLESTEROL,TRIGLICERÍDEOS,LACTATO, FAIXA DE OPERAÇÃO  600 + 300 + 600 MG/DL + 25 MMOL/L, MEMÓRIA ATÉ 150 TESTES, COMPONENTES COM    LANCETAS, TIRAS, ACESSÓRIOS LANCETADOR, SOLUÇÃO CONTROLE",
                "descricaoItem": "MONITOR PORTÁTIL",
                "fornecedorVencedor": null,
                "margemPreferencial": "TRUE",
                "menorLance": "74.40",
                "quantidadeItem": "11",
                "situacaoItem": "homologado",
                "tratamentoDiferenciado": null,
                "unidadeFornecimento": "UNIDADE",
                "valorHomologadoItem": "74.40",
                "valorEstimadoItem": "74.40",
                "valorNegociado": null,
                "idCompra": "15845105000032017",
                "idCompraItem": "1584510500003201700027",
                "noAdjudic": "BIANCA CAROLINA GONCALVES VIANA",
                "noHom": "PAULA VIANNA",
                "dtEncerramento": "2017-10-26",
                "dtAdjudic": "2017-10-27",
                "dtHom": "2017-10-30",
                "dtAlteracao": "2024-04-08T11:32:00"
            },
            {
                "tbVwItensPregaoId": {
                    "coUasg": 158451,
                    "coItem": 19046313
                },
                "decreto7174": "FALSE",
                "descricaoDetalhadaItem": "FRASCO - TIPO ALMOTOLIA, MATERIAL EM POLIETILENO (PLÁSTICO), TIPO BICO BICO   RETO, LONGO, ESTREITO, COM PROTETOR, TIPO TAMPA TAMPA EM ROSCA, COR ÂMBAR,    CAPACIDADE 250 ML",
                "descricaoItem": "FRASCO - TIPO ALMOTOLIA",
                "fornecedorVencedor": null,
                "margemPreferencial": "FALSE",
                "menorLance": "2.90",
                "quantidadeItem": "80",
                "situacaoItem": "homologado",
                "tratamentoDiferenciado": null,
                "unidadeFornecimento": "UNIDADE",
                "valorHomologadoItem": "2.90",
                "valorEstimadoItem": "4.50",
                "valorNegociado": null,
                "idCompra": "15845105000032017",
                "idCompraItem": "1584510500003201700026",
                "noAdjudic": "BIANCA CAROLINA GONCALVES VIANA",
                "noHom": "PAULA VIANNA",
                "dtEncerramento": "2017-10-26",
                "dtAdjudic": "2017-10-27",
                "dtHom": "2017-10-30",
                "dtAlteracao": "2024-04-08T11:32:00"
            },
            {
                "tbVwItensPregaoId": {
                    "coUasg": 158451,
                    "coItem": 19046312
                },
                "decreto7174": "FALSE",
                "descricaoDetalhadaItem": "MEDIDOR, TIPO TRENA ANTROPOMÉTRICA, TIPO MEDIÇÃO MARCAÇÃO EM CENTÍMETROS E    MILÍMETROS, FAIXA TRABALHO 2 M, CARACTERÍSTICAS ADICIONAIS FIBRA VIDRO,       FLEXÍVEL E INELÁSTICA",
                "descricaoItem": "MEDIDOR",
                "fornecedorVencedor": null,
                "margemPreferencial": "FALSE",
                "menorLance": "14.99",
                "quantidadeItem": "11",
                "situacaoItem": "homologado",
                "tratamentoDiferenciado": null,
                "unidadeFornecimento": "UNIDADE",
                "valorHomologadoItem": "14.99",
                "valorEstimadoItem": "15.85",
                "valorNegociado": null,
                "idCompra": "15845105000032017",
                "idCompraItem": "1584510500003201700025",
                "noAdjudic": "BIANCA CAROLINA GONCALVES VIANA",
                "noHom": "PAULA VIANNA",
                "dtEncerramento": "2017-10-26",
                "dtAdjudic": "2017-10-27",
                "dtHom": "2017-10-30",
                "dtAlteracao": "2024-04-08T11:32:00"
            },
            {
                "tbVwItensPregaoId": {
                    "coUasg": 158451,
                    "coItem": 19046311
                },
                "decreto7174": "FALSE",
                "descricaoDetalhadaItem": "FITA HOSPITALAR, TIPO ESPARADRAPO, IMPERMEÁVEL, MATERIAL ALGODÃO, COMPONENTES ADESIVO À BASE DE ZINCO, DIMENSÕES CERCA DE 10 MM, COR COM COR",
                "descricaoItem": "FITA HOSPITALAR",
                "fornecedorVencedor": null,
                "margemPreferencial": "FALSE",
                "menorLance": "6.68",
                "quantidadeItem": "54",
                "situacaoItem": "homologado",
                "tratamentoDiferenciado": null,
                "unidadeFornecimento": "ROLO 4,50 M",
                "valorHomologadoItem": "6.68",
                "valorEstimadoItem": "10.89",
                "valorNegociado": null,
                "idCompra": "15845105000032017",
                "idCompraItem": "1584510500003201700024",
                "noAdjudic": "BIANCA CAROLINA GONCALVES VIANA",
                "noHom": "PAULA VIANNA",
                "dtEncerramento": "2017-10-26",
                "dtAdjudic": "2017-10-27",
                "dtHom": "2017-10-30",
                "dtAlteracao": "2024-04-08T11:32:00"
            },
            {
                "tbVwItensPregaoId": {
                    "coUasg": 158451,
                    "coItem": 19046310
                },
                "decreto7174": "FALSE",
                "descricaoDetalhadaItem": "FITA ADESIVA, MATERIAL CREPE, TIPO MONOFACE, LARGURA 19 MM, COMPRIMENTO 50 M, COR BEGE, APLICAÇÃO MULTIUSO",
                "descricaoItem": "FITA ADESIVA",
                "fornecedorVencedor": null,
                "margemPreferencial": "FALSE",
                "menorLance": "3.00",
                "quantidadeItem": "52",
                "situacaoItem": "homologado",
                "tratamentoDiferenciado": null,
                "unidadeFornecimento": "ROLO 50,00 M",
                "valorHomologadoItem": "3.00",
                "valorEstimadoItem": "7.88",
                "valorNegociado": null,
                "idCompra": "15845105000032017",
                "idCompraItem": "1584510500003201700023",
                "noAdjudic": "BIANCA CAROLINA GONCALVES VIANA",
                "noHom": "PAULA VIANNA",
                "dtEncerramento": "2017-10-26",
                "dtAdjudic": "2017-10-27",
                "dtHom": "2017-10-30",
                "dtAlteracao": "2024-04-08T11:32:00"
            },
            {
                "tbVwItensPregaoId": {
                    "coUasg": 158451,
                    "coItem": 19046309
                },
                "decreto7174": "FALSE",
                "descricaoDetalhadaItem": "FITA HOSPITALAR, TIPO MICROPOROSA, MATERIAL DORSO EM NÃO TECIDO, COMPONENTES  ADESIVO ACRÍLICO, DIMENSÕES CERCA DE 50 MM, CARACTERÍSTICAS ADICIONAIS        HIPOALERGÊNICO, COR COM COR",
                "descricaoItem": "FITA HOSPITALAR",
                "fornecedorVencedor": null,
                "margemPreferencial": "FALSE",
                "menorLance": "4.00",
                "quantidadeItem": "55",
                "situacaoItem": "homologado",
                "tratamentoDiferenciado": null,
                "unidadeFornecimento": "ROLO 10,00 M",
                "valorHomologadoItem": "4.00",
                "valorEstimadoItem": "10.73",
                "valorNegociado": null,
                "idCompra": "15845105000032017",
                "idCompraItem": "1584510500003201700022",
                "noAdjudic": "BIANCA CAROLINA GONCALVES VIANA",
                "noHom": "PAULA VIANNA",
                "dtEncerramento": "2017-10-26",
                "dtAdjudic": "2017-10-27",
                "dtHom": "2017-10-30",
                "dtAlteracao": "2024-04-08T11:32:00"
            },
            {
                "tbVwItensPregaoId": {
                    "coUasg": 158451,
                    "coItem": 19046308
                },
                "decreto7174": "FALSE",
                "descricaoDetalhadaItem": "FITA HOSPITALAR, TIPO MICROPOROSA, MATERIAL DORSO EM NÃO TECIDO, COMPONENTES  ADESIVO ACRÍLICO, DIMENSÕES CERCA DE 25 MM, CARACTERÍSTICAS ADICIONAIS        HIPOALERGÊNICO, COR COM COR",
                "descricaoItem": "FITA HOSPITALAR",
                "fornecedorVencedor": null,
                "margemPreferencial": "FALSE",
                "menorLance": "2.20",
                "quantidadeItem": "55",
                "situacaoItem": "homologado",
                "tratamentoDiferenciado": null,
                "unidadeFornecimento": "ROLO 10,00 M",
                "valorHomologadoItem": "2.20",
                "valorEstimadoItem": "6.88",
                "valorNegociado": null,
                "idCompra": "15845105000032017",
                "idCompraItem": "1584510500003201700021",
                "noAdjudic": "BIANCA CAROLINA GONCALVES VIANA",
                "noHom": "PAULA VIANNA",
                "dtEncerramento": "2017-10-26",
                "dtAdjudic": "2017-10-27",
                "dtHom": "2017-10-30",
                "dtAlteracao": "2024-04-08T11:32:00"
            },
            {
                "tbVwItensPregaoId": {
                    "coUasg": 158451,
                    "coItem": 19046307
                },
                "decreto7174": "FALSE",
                "descricaoDetalhadaItem": "ESTETOSCÓPIO, TIPO BIAURICULAR, ACESSÓRIOS OLIVAS ANATÔMICAS PVC, HASTE HASTE AÇO INOX, TUBO TUBO ´Y´ PVC, AUSCULTADOR AUSCULTADOR AÇO INOX C/ ANEL DE      BORRACHA, TAMANHO ADULTO",
                "descricaoItem": "ESTETOSCÓPIO",
                "fornecedorVencedor": null,
                "margemPreferencial": "FALSE",
                "menorLance": "39.90",
                "quantidadeItem": "6",
                "situacaoItem": "homologado",
                "tratamentoDiferenciado": null,
                "unidadeFornecimento": "UNIDADE",
                "valorHomologadoItem": "39.90",
                "valorEstimadoItem": "98.00",
                "valorNegociado": null,
                "idCompra": "15845105000032017",
                "idCompraItem": "1584510500003201700020",
                "noAdjudic": "BIANCA CAROLINA GONCALVES VIANA",
                "noHom": "PAULA VIANNA",
                "dtEncerramento": "2017-10-26",
                "dtAdjudic": "2017-10-27",
                "dtHom": "2017-10-30",
                "dtAlteracao": "2024-04-08T11:32:00"
            },
            {
                "tbVwItensPregaoId": {
                    "coUasg": 158451,
                    "coItem": 19046306
                },
                "decreto7174": "FALSE",
                "descricaoDetalhadaItem": "ESFIGMOMANÔMETRO, AJUSTE ANALÓGICO, ANERÓIDE, TIPO* DE BRAÇO, FAIXA DE        OPERAÇÃO ATÉ 300 MMHG, MATERIAL BRAÇADEIRA BRAÇADEIRA EM TECIDO, TIPO FECHO   FECHO EM VELCRO, TAMANHO ADULTO",
                "descricaoItem": "ESFIGMOMANÔMETRO",
                "fornecedorVencedor": null,
                "margemPreferencial": "FALSE",
                "menorLance": "77.00",
                "quantidadeItem": "6",
                "situacaoItem": "homologado",
                "tratamentoDiferenciado": null,
                "unidadeFornecimento": "UNIDADE",
                "valorHomologadoItem": "77.00",
                "valorEstimadoItem": "92.29",
                "valorNegociado": null,
                "idCompra": "15845105000032017",
                "idCompraItem": "1584510500003201700019",
                "noAdjudic": "BIANCA CAROLINA GONCALVES VIANA",
                "noHom": "PAULA VIANNA",
                "dtEncerramento": "2017-10-26",
                "dtAdjudic": "2017-10-27",
                "dtHom": "2017-10-30",
                "dtAlteracao": "2024-04-08T11:32:00"
            },
            {
                "tbVwItensPregaoId": {
                    "coUasg": 158451,
                    "coItem": 19046305
                },
                "decreto7174": "FALSE",
                "descricaoDetalhadaItem": "COMPRESSA GAZE, MATERIAL TECIDO 100% ALGODÃO, TIPO 9 FIOS/CM2, MODELO COR     BRANCA,ISENTA DE IMPUREZAS, CAMADAS 8 CAMADAS, LARGURA 10 CM, COMPRIMENTO 10  CM, DOBRAS 5 DOBRAS, CARACTERÍSTICAS ADICIONAIS ESTÉRIL,DESCARTÁVEL",
                "descricaoItem": "COMPRESSA GAZE",
                "fornecedorVencedor": null,
                "margemPreferencial": "FALSE",
                "menorLance": "20.00",
                "quantidadeItem": "32",
                "situacaoItem": "homologado",
                "tratamentoDiferenciado": null,
                "unidadeFornecimento": "PACOTE 500,00 UN",
                "valorHomologadoItem": "20.00",
                "valorEstimadoItem": "32.64",
                "valorNegociado": null,
                "idCompra": "15845105000032017",
                "idCompraItem": "1584510500003201700018",
                "noAdjudic": "BIANCA CAROLINA GONCALVES VIANA",
                "noHom": "PAULA VIANNA",
                "dtEncerramento": "2017-10-26",
                "dtAdjudic": "2017-10-27",
                "dtHom": "2017-10-30",
                "dtAlteracao": "2024-04-08T11:32:00"
            },
            {
                "tbVwItensPregaoId": {
                    "coUasg": 158451,
                    "coItem": 19046304
                },
                "decreto7174": "FALSE",
                "descricaoDetalhadaItem": "COLETOR MATERIAL PÉRFURO-CORTANTE, MATERIAL PAPELÃO, CAPACIDADE TOTAL 3 L,    ACESSÓRIOS ALÇAS RÍGIDAS E TAMPA, COMPONENTES ADICIONAIS REVESTIMENTO INTERNO EM POLIETILENO ALTA DENSIDAD E, TIPO USO DESCARTÁVEL",
                "descricaoItem": "COLETOR MATERIAL PÉRFURO-CORTANTE",
                "fornecedorVencedor": null,
                "margemPreferencial": "FALSE",
                "menorLance": "2.70",
                "quantidadeItem": "210",
                "situacaoItem": "homologado",
                "tratamentoDiferenciado": null,
                "unidadeFornecimento": "UNIDADE",
                "valorHomologadoItem": "2.70",
                "valorEstimadoItem": "5.30",
                "valorNegociado": null,
                "idCompra": "15845105000032017",
                "idCompraItem": "1584510500003201700017",
                "noAdjudic": "BIANCA CAROLINA GONCALVES VIANA",
                "noHom": "PAULA VIANNA",
                "dtEncerramento": "2017-10-26",
                "dtAdjudic": "2017-10-27",
                "dtHom": "2017-10-30",
                "dtAlteracao": "2024-04-08T11:32:00"
            },
            {
                "tbVwItensPregaoId": {
                    "coUasg": 158451,
                    "coItem": 19046303
                },
                "decreto7174": "FALSE",
                "descricaoDetalhadaItem": "COLAR CERVICAL, MATERIAL POLIETILENO, TIPO ADULTO, TIPO FECHAMENTO REGULÁVEL, TRAVAS, FECHO EM VELCRO, USO ABERTURA PARTE FRONTAL, CARACTERÍSTICAS          ADICIONAIS COM SUPORTE MENTONIANO., MATERIAL DO SUPORTE REVESTIDO EM EVA,     CARACTERÍSTICA ADICIONAL RADIOTRANSPARENTE, ABERTURA POSTERIOR",
                "descricaoItem": "COLAR CERVICAL",
                "fornecedorVencedor": null,
                "margemPreferencial": "FALSE",
                "menorLance": "35.81",
                "quantidadeItem": "11",
                "situacaoItem": "homologado",
                "tratamentoDiferenciado": null,
                "unidadeFornecimento": "UNIDADE",
                "valorHomologadoItem": "35.81",
                "valorEstimadoItem": "44.17",
                "valorNegociado": null,
                "idCompra": "15845105000032017",
                "idCompraItem": "1584510500003201700016",
                "noAdjudic": "BIANCA CAROLINA GONCALVES VIANA",
                "noHom": "PAULA VIANNA",
                "dtEncerramento": "2017-10-26",
                "dtAdjudic": "2017-10-27",
                "dtHom": "2017-10-30",
                "dtAlteracao": "2024-04-08T11:32:00"
            },
            {
                "tbVwItensPregaoId": {
                    "coUasg": 158451,
                    "coItem": 19046302
                },
                "decreto7174": "FALSE",
                "descricaoDetalhadaItem": "CLOREXIDINA DIGLUCONATO, DOSAGEM 2%, APLICAÇÃO DEGERMANTE",
                "descricaoItem": "CLOREXIDINA DIGLUCONATO",
                "fornecedorVencedor": null,
                "margemPreferencial": "FALSE",
                "menorLance": "19.00",
                "quantidadeItem": "25",
                "situacaoItem": "homologado",
                "tratamentoDiferenciado": null,
                "unidadeFornecimento": "FRASCO 1.000,00 ML",
                "valorHomologadoItem": "19.00",
                "valorEstimadoItem": "19.55",
                "valorNegociado": null,
                "idCompra": "15845105000032017",
                "idCompraItem": "1584510500003201700015",
                "noAdjudic": "BIANCA CAROLINA GONCALVES VIANA",
                "noHom": "PAULA VIANNA",
                "dtEncerramento": "2017-10-26",
                "dtAdjudic": "2017-10-27",
                "dtHom": "2017-10-30",
                "dtAlteracao": "2024-04-08T11:32:00"
            },
            {
                "tbVwItensPregaoId": {
                    "coUasg": 158451,
                    "coItem": 19046301
                },
                "decreto7174": "FALSE",
                "descricaoDetalhadaItem": "CLOREXIDINA DIGLUCONATO, DOSAGEM 1%, APLICAÇÃO SOLUÇÃO TÓPICA",
                "descricaoItem": "CLOREXIDINA DIGLUCONATO",
                "fornecedorVencedor": null,
                "margemPreferencial": "FALSE",
                "menorLance": "25.00",
                "quantidadeItem": "25",
                "situacaoItem": "cancelado no julgamento",
                "tratamentoDiferenciado": null,
                "unidadeFornecimento": "FRASCO 1.000,00 ML",
                "valorHomologadoItem": null,
                "valorEstimadoItem": "18.78",
                "valorNegociado": null,
                "idCompra": "15845105000032017",
                "idCompraItem": "1584510500003201700014",
                "noAdjudic": "BIANCA CAROLINA GONCALVES VIANA",
                "noHom": "PAULA VIANNA",
                "dtEncerramento": "2017-10-26",
                "dtAdjudic": "2017-10-27",
                "dtHom": "2017-10-30",
                "dtAlteracao": "2024-04-08T11:32:00"
            },
            {
                "tbVwItensPregaoId": {
                    "coUasg": 158451,
                    "coItem": 19046300
                },
                "decreto7174": "FALSE",
                "descricaoDetalhadaItem": "Caixa maleta para ferramentas em material plástico, bandeja com repartições organizadoras com alças, cor preta fechamento com travas de segurança e para uso de lacre ou cadeado tamanho médio dimensões aproximadas: Comp. 49,7cm x alt. 26,5cm x larg. 23,7 cm. Todas as despesas com transporte, entrega, carregamento e descarregamento correrão por conta do licitante.",
                "descricaoItem": "MALETA FERRAMENTAS",
                "fornecedorVencedor": null,
                "margemPreferencial": "FALSE",
                "menorLance": "55.00",
                "quantidadeItem": "11",
                "situacaoItem": "homologado",
                "tratamentoDiferenciado": null,
                "unidadeFornecimento": "UNIDADE",
                "valorHomologadoItem": "55.00",
                "valorEstimadoItem": "57.49",
                "valorNegociado": null,
                "idCompra": "15845105000032017",
                "idCompraItem": "1584510500003201700013",
                "noAdjudic": "BIANCA CAROLINA GONCALVES VIANA",
                "noHom": "PAULA VIANNA",
                "dtEncerramento": "2017-10-26",
                "dtAdjudic": "2017-10-27",
                "dtHom": "2017-10-30",
                "dtAlteracao": "2024-04-08T11:32:00"
            },
            {
                "tbVwItensPregaoId": {
                    "coUasg": 158451,
                    "coItem": 19046299
                },
                "decreto7174": "FALSE",
                "descricaoDetalhadaItem": "BOLSA TÉRMICA, APLICAÇÃO* P/ GELO, MATERIAL* POLÍMERO FLEXÍVEL, MODELO REDONDA, DIÂMETRO* CERCA 20 CM, COMPONENTES C/ TAMPA ROSQUEÁVEL",
                "descricaoItem": "BOLSA TÉRMICA",
                "fornecedorVencedor": null,
                "margemPreferencial": "FALSE",
                "menorLance": "45.00",
                "quantidadeItem": "11",
                "situacaoItem": "homologado",
                "tratamentoDiferenciado": null,
                "unidadeFornecimento": "UNIDADE",
                "valorHomologadoItem": "45.00",
                "valorEstimadoItem": "74.68",
                "valorNegociado": null,
                "idCompra": "15845105000032017",
                "idCompraItem": "1584510500003201700012",
                "noAdjudic": "BIANCA CAROLINA GONCALVES VIANA",
                "noHom": "PAULA VIANNA",
                "dtEncerramento": "2017-10-26",
                "dtAdjudic": "2017-10-27",
                "dtHom": "2017-10-30",
                "dtAlteracao": "2024-04-08T11:32:00"
            },
            {
                "tbVwItensPregaoId": {
                    "coUasg": 158451,
                    "coItem": 19046298
                },
                "decreto7174": "FALSE",
                "descricaoDetalhadaItem": "BOLSA TÉRMICA, APLICAÇÃO* P/ CALOR, MATERIAL* BORRACHA NATURAL, MODELO        RETANGULAR, CAPACIDADE* CERCA 2000 ML, COMPONENTES C/ TAMPA ROSQUEÁVEL",
                "descricaoItem": "BOLSA TÉRMICA",
                "fornecedorVencedor": null,
                "margemPreferencial": "FALSE",
                "menorLance": "45.00",
                "quantidadeItem": "11",
                "situacaoItem": "homologado",
                "tratamentoDiferenciado": null,
                "unidadeFornecimento": "UNIDADE",
                "valorHomologadoItem": "45.00",
                "valorEstimadoItem": "50.27",
                "valorNegociado": null,
                "idCompra": "15845105000032017",
                "idCompraItem": "1584510500003201700011",
                "noAdjudic": "BIANCA CAROLINA GONCALVES VIANA",
                "noHom": "PAULA VIANNA",
                "dtEncerramento": "2017-10-26",
                "dtAdjudic": "2017-10-27",
                "dtHom": "2017-10-30",
                "dtAlteracao": "2024-04-08T11:32:00"
            },
            {
                "tbVwItensPregaoId": {
                    "coUasg": 158451,
                    "coItem": 19046297
                },
                "decreto7174": "FALSE",
                "descricaoDetalhadaItem": "BATERIA NÃO RECARREGÁVEL, TIPO BUTTON CELL, SISTEMA ELETROQUÍMICO LITHIUM,    TENSÃO NOMINAL 3 V, MODELO CR-2032",
                "descricaoItem": "BATERIA NÃO RECARREGÁVEL",
                "fornecedorVencedor": null,
                "margemPreferencial": "FALSE",
                "menorLance": "9.84",
                "quantidadeItem": "21",
                "situacaoItem": "homologado",
                "tratamentoDiferenciado": null,
                "unidadeFornecimento": "EMBALAGEM 5,00 UN",
                "valorHomologadoItem": "9.84",
                "valorEstimadoItem": "10.78",
                "valorNegociado": null,
                "idCompra": "15845105000032017",
                "idCompraItem": "1584510500003201700010",
                "noAdjudic": "BIANCA CAROLINA GONCALVES VIANA",
                "noHom": "PAULA VIANNA",
                "dtEncerramento": "2017-10-26",
                "dtAdjudic": "2017-10-27",
                "dtHom": "2017-10-30",
                "dtAlteracao": "2024-04-08T11:32:00"
            },
            {
                "tbVwItensPregaoId": {
                    "coUasg": 158451,
                    "coItem": 19046296
                },
                "decreto7174": "FALSE",
                "descricaoDetalhadaItem": "ATADURA, MATERIAL CREPOM, 100% ALGODÃO, LARGURA 20 CM, COMPRIMENTO 180 CM,    TIPO EM REPOUSO, QUANTIDADE FIOS 13 UN/CM², TIPO EMBALAGEM EMBALAGEM          INDIVIDUAL",
                "descricaoItem": "ATADURA",
                "fornecedorVencedor": null,
                "margemPreferencial": "FALSE",
                "menorLance": "9.04",
                "quantidadeItem": "205",
                "situacaoItem": "homologado",
                "tratamentoDiferenciado": null,
                "unidadeFornecimento": "UNIDADE",
                "valorHomologadoItem": "9.04",
                "valorEstimadoItem": "17.62",
                "valorNegociado": null,
                "idCompra": "15845105000032017",
                "idCompraItem": "1584510500003201700009",
                "noAdjudic": "BIANCA CAROLINA GONCALVES VIANA",
                "noHom": "PAULA VIANNA",
                "dtEncerramento": "2017-10-26",
                "dtAdjudic": "2017-10-27",
                "dtHom": "2017-10-30",
                "dtAlteracao": "2024-04-08T11:32:00"
            },
            {
                "tbVwItensPregaoId": {
                    "coUasg": 158451,
                    "coItem": 19046295
                },
                "decreto7174": "FALSE",
                "descricaoDetalhadaItem": "ATADURA, MATERIAL CREPOM, 100% ALGODÃO, LARGURA 15 CM, COMPRIMENTO 180 CM,    TIPO EM REPOUSO, QUANTIDADE FIOS 13 UN/CM², TIPO EMBALAGEM EMBALAGEM          INDIVIDUAL",
                "descricaoItem": "ATADURA",
                "fornecedorVencedor": null,
                "margemPreferencial": "FALSE",
                "menorLance": "8.99",
                "quantidadeItem": "205",
                "situacaoItem": "homologado",
                "tratamentoDiferenciado": null,
                "unidadeFornecimento": "UNIDADE",
                "valorHomologadoItem": "8.99",
                "valorEstimadoItem": "15.62",
                "valorNegociado": null,
                "idCompra": "15845105000032017",
                "idCompraItem": "1584510500003201700008",
                "noAdjudic": "BIANCA CAROLINA GONCALVES VIANA",
                "noHom": "PAULA VIANNA",
                "dtEncerramento": "2017-10-26",
                "dtAdjudic": "2017-10-27",
                "dtHom": "2017-10-30",
                "dtAlteracao": "2024-04-08T11:32:00"
            },
            {
                "tbVwItensPregaoId": {
                    "coUasg": 158451,
                    "coItem": 19046294
                },
                "decreto7174": "FALSE",
                "descricaoDetalhadaItem": "ATADURA, MATERIAL CREPOM, 100% ALGODÃO, LARGURA 10 CM, COMPRIMENTO 180 CM,    TIPO EM REPOUSO, QUANTIDADE FIOS 18 UN/CM², TIPO EMBALAGEM EMBALAGEM          INDIVIDUAL",
                "descricaoItem": "ATADURA",
                "fornecedorVencedor": null,
                "margemPreferencial": "FALSE",
                "menorLance": "5.00",
                "quantidadeItem": "205",
                "situacaoItem": "homologado",
                "tratamentoDiferenciado": null,
                "unidadeFornecimento": "UNIDADE",
                "valorHomologadoItem": "5.00",
                "valorEstimadoItem": "10.92",
                "valorNegociado": null,
                "idCompra": "15845105000032017",
                "idCompraItem": "1584510500003201700007",
                "noAdjudic": "BIANCA CAROLINA GONCALVES VIANA",
                "noHom": "PAULA VIANNA",
                "dtEncerramento": "2017-10-26",
                "dtAdjudic": "2017-10-27",
                "dtHom": "2017-10-30",
                "dtAlteracao": "2024-04-08T11:32:00"
            },
            {
                "tbVwItensPregaoId": {
                    "coUasg": 158451,
                    "coItem": 19046293
                },
                "decreto7174": "FALSE",
                "descricaoDetalhadaItem": "ATADURA, MATERIAL CREPOM, 100% ALGODÃO, LARGURA 6 CM, COMPRIMENTO 180 CM, TIPOEM REPOUSO, QUANTIDADE FIOS 13 UN/CM², TIPO EMBALAGEM EMBALAGEM INDIVIDUAL",
                "descricaoItem": "ATADURA",
                "fornecedorVencedor": null,
                "margemPreferencial": "FALSE",
                "menorLance": "2.72",
                "quantidadeItem": "205",
                "situacaoItem": "homologado",
                "tratamentoDiferenciado": null,
                "unidadeFornecimento": "UNIDADE",
                "valorHomologadoItem": "2.72",
                "valorEstimadoItem": "8.51",
                "valorNegociado": null,
                "idCompra": "15845105000032017",
                "idCompraItem": "1584510500003201700006",
                "noAdjudic": "BIANCA CAROLINA GONCALVES VIANA",
                "noHom": "PAULA VIANNA",
                "dtEncerramento": "2017-10-26",
                "dtAdjudic": "2017-10-27",
                "dtHom": "2017-10-30",
                "dtAlteracao": "2024-04-08T11:32:00"
            },
            {
                "tbVwItensPregaoId": {
                    "coUasg": 158451,
                    "coItem": 19046292
                },
                "decreto7174": "FALSE",
                "descricaoDetalhadaItem": "ALGODÃO, TIPO HIDRÓFILO, APRESENTAÇÃO EM ROLETE, MATERIAL ALVEJADO,           PURIFICADO, ISENTO DE IMPUREZAS, ESTERILIDADE NÃO ESTÉRIL",
                "descricaoItem": "ALGODÃO",
                "fornecedorVencedor": null,
                "margemPreferencial": "FALSE",
                "menorLance": "11.75",
                "quantidadeItem": "102",
                "situacaoItem": "homologado",
                "tratamentoDiferenciado": null,
                "unidadeFornecimento": "EMBALAGEM 500,00 G",
                "valorHomologadoItem": "11.75",
                "valorEstimadoItem": "18.93",
                "valorNegociado": null,
                "idCompra": "15845105000032017",
                "idCompraItem": "1584510500003201700005",
                "noAdjudic": "BIANCA CAROLINA GONCALVES VIANA",
                "noHom": "PAULA VIANNA",
                "dtEncerramento": "2017-10-26",
                "dtAdjudic": "2017-10-27",
                "dtHom": "2017-10-30",
                "dtAlteracao": "2024-04-08T11:32:00"
            },
            {
                "tbVwItensPregaoId": {
                    "coUasg": 158451,
                    "coItem": 19046291
                },
                "decreto7174": "FALSE",
                "descricaoDetalhadaItem": "ÁLCOOL ETÍLICO, TIPO HIDRATADO, TEOR ALCOÓLICO 70%_(70¨GL), APRESENTAÇÃO GEL",
                "descricaoItem": "ÁLCOOL ETÍLICO",
                "fornecedorVencedor": null,
                "margemPreferencial": "FALSE",
                "menorLance": "38.00",
                "quantidadeItem": "120",
                "situacaoItem": "homologado",
                "tratamentoDiferenciado": null,
                "unidadeFornecimento": "GALÃO 5,00 L",
                "valorHomologadoItem": "38.00",
                "valorEstimadoItem": "49.17",
                "valorNegociado": null,
                "idCompra": "15845105000032017",
                "idCompraItem": "1584510500003201700004",
                "noAdjudic": "BIANCA CAROLINA GONCALVES VIANA",
                "noHom": "PAULA VIANNA",
                "dtEncerramento": "2017-10-26",
                "dtAdjudic": "2017-10-27",
                "dtHom": "2017-10-30",
                "dtAlteracao": "2024-04-08T11:32:00"
            },
            {
                "tbVwItensPregaoId": {
                    "coUasg": 158451,
                    "coItem": 19046290
                },
                "decreto7174": "FALSE",
                "descricaoDetalhadaItem": "ÁLCOOL ETÍLICO, TIPO HIDRATADO, TEOR ALCOÓLICO 70%_(70¨GL), APRESENTAÇÃO      LÍQUIDO",
                "descricaoItem": "ÁLCOOL ETÍLICO",
                "fornecedorVencedor": null,
                "margemPreferencial": "FALSE",
                "menorLance": "36.88",
                "quantidadeItem": "33",
                "situacaoItem": "homologado",
                "tratamentoDiferenciado": null,
                "unidadeFornecimento": "GALÃO 5,00 L",
                "valorHomologadoItem": "36.88",
                "valorEstimadoItem": "51.28",
                "valorNegociado": null,
                "idCompra": "15845105000032017",
                "idCompraItem": "1584510500003201700003",
                "noAdjudic": "BIANCA CAROLINA GONCALVES VIANA",
                "noHom": "PAULA VIANNA",
                "dtEncerramento": "2017-10-26",
                "dtAdjudic": "2017-10-27",
                "dtHom": "2017-10-30",
                "dtAlteracao": "2024-04-08T11:32:00"
            },
            {
                "tbVwItensPregaoId": {
                    "coUasg": 158451,
                    "coItem": 19046289
                },
                "decreto7174": "FALSE",
                "descricaoDetalhadaItem": "ÁGUA DESTILADA, ASPECTO FÍSICO LÍQUIDO INCOLOR, INODORO, INSÍPIDO,            CARACTERÍSTICAS ADICIONAIS CONFORME FARMACOPÉIA BRASILEIRA",
                "descricaoItem": "ÁGUA DESTILADA",
                "fornecedorVencedor": null,
                "margemPreferencial": "FALSE",
                "menorLance": "9.90",
                "quantidadeItem": "33",
                "situacaoItem": "homologado",
                "tratamentoDiferenciado": null,
                "unidadeFornecimento": "GALÃO 5,00 L",
                "valorHomologadoItem": "9.90",
                "valorEstimadoItem": "11.42",
                "valorNegociado": null,
                "idCompra": "15845105000032017",
                "idCompraItem": "1584510500003201700002",
                "noAdjudic": "BIANCA CAROLINA GONCALVES VIANA",
                "noHom": "PAULA VIANNA",
                "dtEncerramento": "2017-10-26",
                "dtAdjudic": "2017-10-27",
                "dtHom": "2017-10-30",
                "dtAlteracao": "2024-04-08T11:32:00"
            },
            {
                "tbVwItensPregaoId": {
                    "coUasg": 158451,
                    "coItem": 19046288
                },
                "decreto7174": "FALSE",
                "descricaoDetalhadaItem": "ABAIXADOR LÍNGUA, MATERIAL MADEIRA, TIPO DESCARTÁVEL, COMPRIMENTO 14 CM,      FORMATO TIPO ESPÁTULA, EMBALAGEM INDIVIDUAL, LARGURA 1,50 CM, ESPESSURA 2 MM",
                "descricaoItem": "ABAIXADOR LÍNGUA",
                "fornecedorVencedor": null,
                "margemPreferencial": "FALSE",
                "menorLance": "3.20",
                "quantidadeItem": "22",
                "situacaoItem": "homologado",
                "tratamentoDiferenciado": null,
                "unidadeFornecimento": "PACOTE 100,00 UN",
                "valorHomologadoItem": "3.20",
                "valorEstimadoItem": "6.27",
                "valorNegociado": null,
                "idCompra": "15845105000032017",
                "idCompraItem": "1584510500003201700001",
                "noAdjudic": "BIANCA CAROLINA GONCALVES VIANA",
                "noHom": "PAULA VIANNA",
                "dtEncerramento": "2017-10-26",
                "dtAdjudic": "2017-10-27",
                "dtHom": "2017-10-30",
                "dtAlteracao": "2024-04-08T11:32:00"
            },
            {
                "tbVwItensPregaoId": {
                    "coUasg": 158451,
                    "coItem": 19046324
                },
                "decreto7174": "FALSE",
                "descricaoDetalhadaItem": "MACA DE RESGATE, MATERIAL MADEIRA COMPENSADA, TIPO PRANCHA, TAMANHO ADULTO,   LARGURA CERCA DE 0,60 M, FORMATO FORMATO ANATÔMICO, COMPONENTES ATÉ 5 CINTOS  DE SEGURANÇA",
                "descricaoItem": "MACA DE RESGATE",
                "fornecedorVencedor": null,
                "margemPreferencial": "FALSE",
                "menorLance": "234.99",
                "quantidadeItem": "11",
                "situacaoItem": "homologado",
                "tratamentoDiferenciado": null,
                "unidadeFornecimento": "UNIDADE",
                "valorHomologadoItem": "234.99",
                "valorEstimadoItem": "329.84",
                "valorNegociado": null,
                "idCompra": "15845105000032017",
                "idCompraItem": "1584510500003201700037",
                "noAdjudic": "BIANCA CAROLINA GONCALVES VIANA",
                "noHom": "PAULA VIANNA",
                "dtEncerramento": "2017-10-26",
                "dtAdjudic": "2017-10-27",
                "dtHom": "2017-10-30",
                "dtAlteracao": "2024-04-08T11:32:00"
            },
            {
                "tbVwItensPregaoId": {
                    "coUasg": 158451,
                    "coItem": 19046323
                },
                "decreto7174": "FALSE",
                "descricaoDetalhadaItem": "Óleo de girassol (a cidos graxos essenciais insaturados ole icos: a cido linole nico e linoleico, Vitamina A, Vitamina E e Lecitina de soja) - Embalagem com no minimo 200 ml. Todas as despesas com transporte, entrega, carregamento e descarregamento correrão por conta do licitante.",
                "descricaoItem": "OLEO COMESTIVEL",
                "fornecedorVencedor": null,
                "margemPreferencial": "FALSE",
                "menorLance": "28.98",
                "quantidadeItem": "15",
                "situacaoItem": "homologado",
                "tratamentoDiferenciado": null,
                "unidadeFornecimento": "UNIDADE",
                "valorHomologadoItem": "28.98",
                "valorEstimadoItem": "32.01",
                "valorNegociado": null,
                "idCompra": "15845105000032017",
                "idCompraItem": "1584510500003201700036",
                "noAdjudic": "BIANCA CAROLINA GONCALVES VIANA",
                "noHom": "PAULA VIANNA",
                "dtEncerramento": "2017-10-26",
                "dtAdjudic": "2017-10-27",
                "dtHom": "2017-10-30",
                "dtAlteracao": "2024-04-08T11:32:00"
            },
            {
                "tbVwItensPregaoId": {
                    "coUasg": 158451,
                    "coItem": 19046322
                },
                "decreto7174": "FALSE",
                "descricaoDetalhadaItem": "ÓCULOS PROTEÇÃO, MATERIAL ARMAÇÃO POLICARBONATO, TIPO PROTEÇÃO LATERAL, COR   LENTE INCOLOR, APLICAÇÃO PROTEÇÃO GERAL, CARACTERÍSTICAS ADICIONAIS RESISTENTEA IMPACTOS",
                "descricaoItem": "ÓCULOS PROTEÇÃO",
                "fornecedorVencedor": null,
                "margemPreferencial": "FALSE",
                "menorLance": "2.96",
                "quantidadeItem": "201",
                "situacaoItem": "homologado",
                "tratamentoDiferenciado": null,
                "unidadeFornecimento": "UNIDADE",
                "valorHomologadoItem": "2.96",
                "valorEstimadoItem": "12.27",
                "valorNegociado": null,
                "idCompra": "15845105000032017",
                "idCompraItem": "1584510500003201700035",
                "noAdjudic": "BIANCA CAROLINA GONCALVES VIANA",
                "noHom": "PAULA VIANNA",
                "dtEncerramento": "2017-10-26",
                "dtAdjudic": "2017-10-27",
                "dtHom": "2017-10-30",
                "dtAlteracao": "2024-04-08T11:32:00"
            },
            {
                "tbVwItensPregaoId": {
                    "coUasg": 158451,
                    "coItem": 19046321
                },
                "decreto7174": "FALSE",
                "descricaoDetalhadaItem": "MÁSCARA CIRÚRGICA, TIPO NÃO TECIDO,3 CAMADAS,PREGAS HORIZONTAIS,ATÓXICA, TIPO FIXAÇÃO 4 TIRAS LATERAIS P/ FIXAÇÃO, CARACTERÍSTICAS ADICIONAIS CLIP NASAL    EMBUTIDO,HIPOALERGÊNICA, COR AZUL, TIPO USO DESCARTÁVEL",
                "descricaoItem": "MÁSCARA CIRÚRGICA",
                "fornecedorVencedor": null,
                "margemPreferencial": "FALSE",
                "menorLance": "5.55",
                "quantidadeItem": "305",
                "situacaoItem": "homologado",
                "tratamentoDiferenciado": null,
                "unidadeFornecimento": "UNIDADE",
                "valorHomologadoItem": "5.55",
                "valorEstimadoItem": "10.33",
                "valorNegociado": null,
                "idCompra": "15845105000032017",
                "idCompraItem": "1584510500003201700034",
                "noAdjudic": "BIANCA CAROLINA GONCALVES VIANA",
                "noHom": "PAULA VIANNA",
                "dtEncerramento": "2017-10-26",
                "dtAdjudic": "2017-10-27",
                "dtHom": "2017-10-30",
                "dtAlteracao": "2024-04-08T11:32:00"
            }
        ],
        "totalRegistros": 47,
        "totalPaginas": 1,
        "paginasRestantes": 0
    }
}